penin/__init__.py
penin/bootstrap.py
penin/constants.py
penin/main.py
penin/controllers/__init__.py
penin/controllers/arp.py
penin/controllers/base.py
penin/controllers/dns.py
penin/controllers/http.py
penin/controllers/icmp.py
penin/controllers/ip.py
penin/controllers/misc.py
penin/controllers/port_scan.py
penin/controllers/whois.py
penin/core/__init__.py
penin/core/exc.py
penin/core/version.py
penin/core/arp/__init__.py
penin/core/dns/__init__.py
penin/core/http/__init__.py
penin/core/icmp/__init__.py
penin/core/ip/__init__.py
penin/core/port_scan/__init__.py
penin/core/whois/__init__.py
penin/ext/__init__.py
penin/helpers/__init__.py
penin/plugins/__init__.py
penin/templates/__init__.py
penin/templates/default.jinja2
penin-0.1.0.dist-info/LICENSE.md
penin-0.1.0.dist-info/METADATA
penin-0.1.0.dist-info/WHEEL
penin-0.1.0.dist-info/entry_points.txt
penin-0.1.0.dist-info/top_level.txt
penin-0.1.0.dist-info/RECORD
