Metadata-Version: 2.1
Name: penin
Version: 0.1.0
Summary: Information gathering and penetration testing framework
Home-page: https://github.com/fabaff/penin
Author: Fabian Affolter
Author-email: fabian@affolter-engineering.ch
License: Apache 2.0
Keywords: home,automation
Platform: any
Classifier: Development Status :: 3 - Alpha
Classifier: Intended Audience :: End Users/Desktop
Classifier: Intended Audience :: Developers
Classifier: License :: OSI Approved :: Apache Software License
Classifier: Operating System :: OS Independent
Classifier: Programming Language :: Python :: 3.5
Classifier: Programming Language :: Python :: 3.6
Classifier: Programming Language :: Python :: 3.7
Classifier: Topic :: Home Automation
Requires-Dist: cement
Requires-Dist: pyyaml
Requires-Dist: colorlog
Requires-Dist: jinja2
Requires-Dist: tinydb
